statusmsg/__init__.py
statusmsg/colors.py
statusmsg/movement.py
statusmsg/status.py
statusmsg-1.0.0.dist-info/DESCRIPTION.rst
statusmsg-1.0.0.dist-info/METADATA
statusmsg-1.0.0.dist-info/RECORD
statusmsg-1.0.0.dist-info/WHEEL
statusmsg-1.0.0.dist-info/metadata.json
statusmsg-1.0.0.dist-info/top_level.txt
